setup.py
redcrab/__init__.py
redcrab/constants.py
redcrab/crawler.py
redcrab/main.py
redcrab/postgres.py
redcrab.egg-info/PKG-INFO
redcrab.egg-info/SOURCES.txt
redcrab.egg-info/dependency_links.txt
redcrab.egg-info/entry_points.txt
redcrab.egg-info/requires.txt
redcrab.egg-info/top_level.txt