Metadata-Version: 1.0
Name: redcrab
Version: 0.1.1
Summary: A crawler for the Reddit API that will take comments and store them in a database
Home-page: UNKNOWN
Author: Gregory Rehm
Author-email: UNKNOWN
License: UNKNOWN
Platform: UNKNOWN
